oremi_idatha_models/__init__.py
oremi_idatha_models/activity.py
oremi_idatha_models/api.py
oremi_idatha_models/assistant.py
oremi_idatha_models/couch.py
oremi_idatha_models/device.py
oremi_idatha_models/document.py
oremi_idatha_models/setting.py
oremi_idatha_models/user.py
oremi_idatha_models/version.py
oremi_idatha_models-1.0.0b252.dist-info/METADATA
oremi_idatha_models-1.0.0b252.dist-info/WHEEL
oremi_idatha_models-1.0.0b252.dist-info/licenses/LICENSE
oremi_idatha_models-1.0.0b252.dist-info/RECORD
