Metadata-Version: 2.4
Name: oremi-idatha-models
Version: 1.0.0b252
Summary: Shared models for Oremi Idatha
Project-URL: Say Thanks!, https://www.buymeacoffee.com/demsking
Project-URL: Documentation, https://demsking.gitlab.io/oremi-idatha
Project-URL: Source, https://gitlab.com/demsking/oremi-idatha
Project-URL: Issues, https://gitlab.com/demsking/oremi-idatha/-/issues
Author-email: Sébastien Demanou <demsking@gmail.com>
Maintainer-email: Sébastien Demanou <demsking@gmail.com>
License-Expression: Apache-2.0
License-File: LICENSE
Keywords: api,models,oremi,restfull
Classifier: Development Status :: 4 - Beta
Classifier: Intended Audience :: Developers
Classifier: Programming Language :: Python :: 3.11
Requires-Python: <3.12,>=3.11
